universal_timeseries_transformer/__init__.py
universal_timeseries_transformer/dataframe_transformer.py
universal_timeseries_transformer/index_transformer.py
universal_timeseries_transformer/index_validator.py
universal_timeseries_transformer/timeseries_application.py
universal_timeseries_transformer/timeseries_basis.py
universal_timeseries_transformer/timeseries_decomposer.py
universal_timeseries_transformer/timeseries_extender.py
universal_timeseries_transformer/timeseries_slicer.py
universal_timeseries_transformer/timeseries_splitter.py
universal_timeseries_transformer/timeseries_transformer.py
universal_timeseries_transformer/matrix_representation/__init__.py
universal_timeseries_transformer/matrix_representation/prices_matrix.py
universal_timeseries_transformer/matrix_representation/timeseries_matrix.py
universal_timeseries_transformer/visualizer/__init__.py
universal_timeseries_transformer/visualizer/basis.py
universal_timeseries_transformer/visualizer/utils.py
universal_timeseries_transformer-0.3.9.data/data/requirements.txt
universal_timeseries_transformer-0.3.9.dist-info/METADATA
universal_timeseries_transformer-0.3.9.dist-info/WHEEL
universal_timeseries_transformer-0.3.9.dist-info/top_level.txt
universal_timeseries_transformer-0.3.9.dist-info/RECORD
