Metadata-Version: 2.4
Name: universal_timeseries_transformer
Version: 0.3.9
Summary: A package for transforming and manipulating time series data with universal interfaces
Home-page: https://github.com/nailen1/universal_timeseries_transformer
Author: June Young Park
Author-email: juneyoungpaak@gmail.com
Classifier: Development Status :: 3 - Alpha
Classifier: Intended Audience :: Developers
Classifier: Intended Audience :: Science/Research
Classifier: License :: OSI Approved :: MIT License
Classifier: Programming Language :: Python :: 3
Classifier: Programming Language :: Python :: 3.8
Classifier: Programming Language :: Python :: 3.9
Classifier: Programming Language :: Python :: 3.10
Classifier: Programming Language :: Python :: 3.11
Requires-Python: >=3.8
Requires-Dist: pandas
Requires-Dist: matplotlib
Requires-Dist: string_date_controller>=0.3.0
Dynamic: author
Dynamic: author-email
Dynamic: classifier
Dynamic: description
Dynamic: description-content-type
Dynamic: home-page
Dynamic: requires-dist
Dynamic: requires-python
Dynamic: summary
